{
      "4fb4afc64f1d794ae904d39a1ca5ebd1": {
        "img": "https://blog.cex.io/wp-content/uploads/2024/07/1.1_1080%D1%851080.webp",
        "tag": "Education",
        "title": "Rising from the Ashes: Telegram’s Push for a User-Centric Web3 and Crypto Experience",
        "summary": "Since 2013, Telegram has been at the forefront of digital communications, and made repeated drives toward advancing greater crypto adoption.",
        "date": "Jul 01, 2024",
        "readTime": "13 min read",
        "article": {}
    },
    "af5542bbd480ccca78cd6abd617d9120": {
        "key": "bitcoin",
        "name": "Bitcoin",
        "symbol": "BTC",
        "amount": "0.006",
        "paid": "404.17",
        "notes": "",
        "_id": "5e3e921f-285e-47da-8cfe-aaa7bfd4a969"
    }
}